nbplugins_watch/__init__.py
nbplugins_watch/nbplugins_watch.py
nbplugins_watch-0.0.6.dist-info/LICENSE
nbplugins_watch-0.0.6.dist-info/WHEEL
nbplugins_watch-0.0.6.dist-info/METADATA
nbplugins_watch-0.0.6.dist-info/RECORD
