Metadata-Version: 2.1
Name: nbplugins-watch
Version: 0.0.6
Summary: watch and (re)load/remove nonebot plugins from a directory
Home-page: https://github.com/ffreemt/nonebot-plugins-watch
Author: ffreemt
Requires-Python: >=3.7,<4.0
Classifier: Programming Language :: Python :: 3
Classifier: Programming Language :: Python :: 3.7
Classifier: Programming Language :: Python :: 3.8
Requires-Dist: logzero (>=1.5.0,<2.0.0)
Requires-Dist: nonebot (>=1.6.0,<2.0.0)
Requires-Dist: watchgod (>=0.6,<0.7)
Project-URL: Repository, https://github.com/ffreemt/nonebot-plugins-watch
